setup.cfg
setup.py
WSGIProfile.egg-info/PKG-INFO
WSGIProfile.egg-info/SOURCES.txt
WSGIProfile.egg-info/dependency_links.txt
WSGIProfile.egg-info/entry_points.txt
WSGIProfile.egg-info/not-zip-safe
WSGIProfile.egg-info/requires.txt
WSGIProfile.egg-info/top_level.txt
wsgiprofile/__init__.py
wsgiprofile/controllers.py
wsgiprofile/middleware.py
wsgiprofile/stats.py