Metadata-Version: 1.0
Name: WSGIProfile
Version: 0.1dev
Summary: WSGI Middleware for embedding a rich profiler in web pages.
Home-page: UNKNOWN
Author: Stephen Emslie
Author-email: stephenemslie@gmail.com
License: UNKNOWN
Keywords: profile profiling wsgi middleware
Platform: UNKNOWN
Classifier: Topic :: Software Development :: Debuggers
Classifier: Topic :: Internet :: WWW/HTTP :: WSGI :: Middleware
Classifier: Intended Audience :: Developers
Classifier: Programming Language :: Python
Classifier: Environment :: Web Environment
Classifier: Operating System :: MacOS :: MacOS X
Classifier: Operating System :: Microsoft :: Windows
Classifier: Operating System :: POSIX
